no_floc/__init__.py
no_floc/apps.py
no_floc/middleware.py
django_no_floc-0.1.0.dist-info/AUTHORS.rst
django_no_floc-0.1.0.dist-info/LICENSE
django_no_floc-0.1.0.dist-info/METADATA
django_no_floc-0.1.0.dist-info/WHEEL
django_no_floc-0.1.0.dist-info/top_level.txt
django_no_floc-0.1.0.dist-info/RECORD
