Metadata-Version: 2.1
Name: django-no-floc
Version: 0.1.0
Summary: Middleware to opt out of Google's FLoC cohort tracking.
Home-page: https://github.com/ph00lt0/django-no-floc
Author: ph00lt0
Author-email: you@example.com
License: MIT
Keywords: django-no-floc
Platform: UNKNOWN
Classifier: Development Status :: 3 - Alpha
Classifier: Framework :: Django :: 1.11
Classifier: Framework :: Django :: 2.1
Classifier: Intended Audience :: Developers
Classifier: License :: OSI Approved :: BSD License
Classifier: Natural Language :: English
Classifier: Programming Language :: Python :: 2
Classifier: Programming Language :: Python :: 2.7
Classifier: Programming Language :: Python :: 3
Classifier: Programming Language :: Python :: 3.5
Classifier: Programming Language :: Python :: 3.6
